falcon_raml-0.1.0.dist-info/DESCRIPTION.rst
falcon_raml-0.1.0.dist-info/METADATA
falcon_raml-0.1.0.dist-info/RECORD
falcon_raml-0.1.0.dist-info/WHEEL
falcon_raml-0.1.0.dist-info/metadata.json
falcon_raml-0.1.0.dist-info/top_level.txt
falconraml/__init__.py
falconraml/jsontranslator.py
falconraml/parameterchecker.py
